{
  "navigation": {
    "deposit": "Deposit",
    "borrow": "Borrow",
    "dashboard": "Dashboard"
  },
  "pages": {
    "deposit": {
      "main": {
        "header": "Supply",
        "form": {
          "depositTitle": "Deposit",
          "approveTitle": "Approve",
          "CTA": "Deposit"
        }
      },
      "metrics": {
        "header": "Summary",
        "depositAPYTitle": "Deposit APY",
        "assetPriceTitle": "Asset price",
        "walletBalanceTitle": "Wallet balance"
      }
    },
    "borrow": {
      "main": {
        "header": "Borrow",
        "form": {
          "step1": {
            "description": "Select your loan type",
            "unsecuredLoanCard": {
              "title": "Unsecured loan",
              "description": "Apply for an unsecured loan by connecting your bank account."
            },
            "securedLoanCard": {
              "title": "Secured loan",
              "description": "Apply for a secured loan, no bank account needed."
            }
          },
          "step2": {},
          "step3": {},
          "step4": {}
        }
      },
      "metrics": {
        "header": "Summary",
        "assetPriceTitle": "Asset price",
        "walletBalanceTitle": "Wallet balance",
        "collateralAvailableTitle": "Collateral available"
      }
    },
    "dashboard": {
      "loggedOutMessage": "Please connect your wallet to view the dashboard.",
      "deposit-redeem": {
        "header": "Redeem",
        "description": "Select an asset to redeem your APY to date.",
        "assetChangeWarningMessage": "Redeeming your APY will submit a transaction and incur gas fees. Costs will be debited from your wallet. Are you sure you want to proceed?",
        "claimCTA": "Claim",
        "redeemCTA": "Redeem"
      },
      "deposit-withdraw": {
        "header": "Withdraw",
        "description": "Select an asset to withdraw your deposit to date.",
        "form": { "withdrawWithTitle": "Withdraw with" }
      },
      "borrow-repay": {
        "header": "Repay"
      },
      "borrow-deposit": {
        "header": "Deposit Collateral",
        "description": "Deposit additional collateral for an outstanding loan."
      },
      "borrow-withdraw": {
        "header": "Withdraw Collateral",
        "description": "Select the loan you want to withdraw collateral from."
      },
      "spend-compound": {
        "header": "Compound",
        "description": "Select the loan you want to withdraw into."
      },
      "spend-uniswap": {
        "header": "Uniswap",
        "description": "Swap your assets with Uniswap."
      }
    }
  },
  "CTAs": {
    "loginButtonTitle": "Connect Wallet"
  },
  "footer": {
    "urls": [
      {
        "title": "Privacy",
        "url": "https://app.termly.io/document/privacy-policy/398c0f5b-02f5-4078-8dd7-72c1cd25c56a"
      },
      {
        "title": "Terms",
        "url": "https://app.termly.io/document/terms-of-use-for-website/21b27900-06c4-4b4d-bc95-73642b34e437"
      },
      {
        "title": "Disclaimer",
        "url": "https://app.termly.io/document/disclaimer/3115ce72-c995-48f8-905c-9219d109d32b"
      }
    ]
  }
}
